linux_drivers/__init__.py
linux_drivers/bluetooth/__init__.py
linux_drivers/bluetooth/bth_1208LS.py
linux_drivers/bluetooth/mccBluetooth.py
linux_drivers/bluetooth/test-bth1208LS.py
linux_drivers/ethernet/E_1608.py
linux_drivers/ethernet/E_DIO24.py
linux_drivers/ethernet/E_TC.py
linux_drivers/ethernet/E_TC32.py
linux_drivers/ethernet/__init__.py
linux_drivers/ethernet/mccEthernet.py
linux_drivers/ethernet/test-E-1608.py
linux_drivers/ethernet/test-E-DIO24.py
linux_drivers/ethernet/test-E-TC.py
linux_drivers/ethernet/test-E-TC32.py
linux_drivers/usb/__init__.py
linux_drivers/usb/bth_1208LS.py
linux_drivers/usb/mccUSB.py
linux_drivers/usb/test-bth1208LS.py
linux_drivers/usb/test-miniLAB.py
linux_drivers/usb/test-usb-20x.py
linux_drivers/usb/test-usb-DIO24.py
linux_drivers/usb/test-usb-DIO24H.py
linux_drivers/usb/test-usb-ctr.py
linux_drivers/usb/test-usb-dio96H.py
linux_drivers/usb/test-usb-erb08.py
linux_drivers/usb/test-usb-erb24.py
linux_drivers/usb/test-usb-pdiso8.py
linux_drivers/usb/test-usb-ssr08.py
linux_drivers/usb/test-usb-ssr24.py
linux_drivers/usb/test-usb-temp.py
linux_drivers/usb/test-usb1024HLS.py
linux_drivers/usb/test-usb1024LS.py
linux_drivers/usb/test-usb1208FS.py
linux_drivers/usb/test-usb1208LS.py
linux_drivers/usb/test-usb1408FS.py
linux_drivers/usb/test-usb1608FS.py
linux_drivers/usb/test-usb1616FS.py
linux_drivers/usb/test-usb2001tc.py
linux_drivers/usb/test-usb2408.py
linux_drivers/usb/test-usb2416.py
linux_drivers/usb/test-usb3100.py
linux_drivers/usb/thermocouple.py
linux_drivers/usb/usb_1208FS.py
linux_drivers/usb/usb_1208LS.py
linux_drivers/usb/usb_1408FS.py
linux_drivers/usb/usb_1608FS.py
linux_drivers/usb/usb_1616FS.py
linux_drivers/usb/usb_2001TC.py
linux_drivers/usb/usb_20x.py
linux_drivers/usb/usb_2400.py
linux_drivers/usb/usb_3100.py
linux_drivers/usb/usb_ctr.py
linux_drivers/usb/usb_ctr_rbf.py
linux_drivers/usb/usb_dioLS.py
linux_drivers/usb/usb_dioSS.py
linux_drivers/usb/usb_temp.py
linux_drivers-0.0.3.dist-info/METADATA
linux_drivers-0.0.3.dist-info/WHEEL
linux_drivers-0.0.3.dist-info/top_level.txt
linux_drivers-0.0.3.dist-info/RECORD
