Metadata-Version: 2.1
Name: linux-drivers
Version: 0.0.3
Summary: Open source Linux device drivers for Python 3.
Home-page: https://github.com/wjasper/Linux_Drivers
Author: Warren J. Jasper
Author-email: wjasper@ncsu.edu
License: UNKNOWN
Platform: UNKNOWN
Requires-Python: >=3.6
Requires-Dist: pybluez
